LICENSE
README.md
setup.py
tropygal/DFs.py
tropygal/__init__.py
tropygal/base_funcs.py
tropygal/constants.py
tropygal/potentials.py
tropygal.egg-info/PKG-INFO
tropygal.egg-info/SOURCES.txt
tropygal.egg-info/dependency_links.txt
tropygal.egg-info/requires.txt
tropygal.egg-info/top_level.txt