Metadata-Version: 2.1
Name: tropygal
Version: 0.1.1
Summary: Entropy estimators for galactic dynamics
Author: Leandro Beraldo e Silva
Author-email: lberaldoesilva@gmail.com
License: MIT
Requires-Python: >=3
License-File: LICENSE
Requires-Dist: numpy
Requires-Dist: scipy
